describecsv/__init__.py
describecsv/describecsv.py
describecsv/markdown_output.py
describecsv-1.0.0.dist-info/METADATA
describecsv-1.0.0.dist-info/WHEEL
describecsv-1.0.0.dist-info/entry_points.txt
describecsv-1.0.0.dist-info/licenses/LICENSE
describecsv-1.0.0.dist-info/RECORD
