Metadata-Version: 2.4
Name: describecsv
Version: 1.0.0
Summary: A tool for analyzing and describing CSV files
Project-URL: Homepage, https://github.com/nealcaren/describecsv
Project-URL: Bug Tracker, https://github.com/nealcaren/describecsv/issues
Project-URL: Documentation, https://github.com/nealcaren/describecsv#readme
Author-email: Neal Caren <neal.caren@unc.edu>
License-File: LICENSE
Classifier: License :: OSI Approved :: MIT License
Classifier: Operating System :: OS Independent
Classifier: Programming Language :: Python :: 3
Requires-Python: >=3.10
Requires-Dist: chardet
Requires-Dist: numpy
Requires-Dist: pandas
Requires-Dist: python-dateutil
Requires-Dist: pytz
Requires-Dist: tqdm
Requires-Dist: tzdata
